Workbook

Sheet Notes
A1: Comprehensive Statutroy Acts & Legal Frameworks Matrix (Rwanda)
A2: This matrix outlines the key Statutory Acts & Legal References for statutory PAYE tax limits, rates, levies and reliefts.
A4: Income Tax Law of 2022 (Law N° 027/2022)
A5: Description | B5: Reference | C5: Limit
A6: Personal Relief | B6: N/A | C6: None. PAYE is applied via progressive bands; the monthly tax-free threshold is RWF 60,000 (then 10%, 20%, 30%). No personal reliefs provided by law (other than wholly-and-exclusively employment expenses).
A7: Insurance Relief | B7: N/A | C7: None. PAYE is applied via progressive bands; the monthly tax-free threshold is RWF 60,000 (then 10%, 20%, 30%). No personal reliefs provided by law (other than wholly-and-exclusively employment expenses).
A8: Medical reimbursements / employer medical insurance | B8: RRA PAYE guidance (employment income scope) | C8: Bona fide business/medical reimbursements paid on behalf of the employee are not part of taxable employment income when they are genuine reimbursements (documented). No explicit shilling cap.
A9: Business travel & accommodation (in course of duty) | B9: RRA PAYE guide | C9: Excluded from taxable employment income when incurred or likely to be incurred in performing duties (keep receipts/policy).
A10: Housing / car / low-interest loan (benefit valuation) | B10: RRA PAYE guide | C10: Taxable benefits (include in PAYE) per RRA benefit rules; no special personal deductions.
A11: Rwanda Social Security Board (RSSB) Act (Law N° 009/2021)
A12: Description | B12: Reference | C12: Limit
A13: Pension – compulsory scheme | B13: RSSB Law N° 009/2021 | C13: Total 12% of gross/basic salary from Jan 2025, split 6% employer + 6% employee (previously 3%+3%).
A14: Medical insurance (formal sector) | B14: RSSB Law N° 009/2022 | C14: 15% of basic salary (7.5% employer + 7.5% employee). Paid monthly via employer to RSSB
A15: Maternity Leave Insurance | B15: RSSB Law N° 009/2023 | C15: 0.6% of gross salary (0.3% employer + 0.3% employee). Employer pays full 12-week leave and seeks RSSB reimbursement for the last 6 weeks.
A16: None
A17: Description | B17: Reference | C17: Limit
A18: AHL | B18: N/A | C18: None.
A19: None
A20: Description | B20: Reference | C20: Limit
A21: Pension and provident fund contributions and benefit deductions | B21: N/A | C21: N/A
A22: Rwanda's Employment Law (Law N° 66/2018, which has been amended by Law N° 027/2023)
A23: Description | B23: Reference | C23: Limit
A24: Permitted deductions / cap | B24: Law No. 66/2018 regulating Labour | C24: Deductions must be lawful/consented; practical cap per 2018 law commentary: total deductions must not exceed 50% of salary (older 2009 law had one-third cap). Align your payroll policy to the current 2018 law and keep written consent.
A25: EWA (earned-wage access) / advances | B25: Labour law framework | C25: Treat as advance of earned wages, not a credit facility, provided the employee consents and deductions respect the overall cap above and appear on the payslip.
A26: Feature | B26: Earned Wage Access (EWA) | C26: Traditional Loan
A27: Source of funds | B27: Employee’s already earned salary (portion of wages due) | C27: Third-party credit not yet earned
A28: Legal classification | B28: Wage advance under labour law; payroll deduction with consent and within statutory cap | C28: Credit facility under banking/microfinance law
A29: Interest or finance charge | B29: Typically service fee (not interest) if kept as wage advance | C29: Interest-bearing under finance laws
A30: Repayment source | B30: Payroll deduction from subsequent salary (within cap) | C30: Installments from future income
A31: Regulatory body | B31: National Bank of Rwanda (BNR) only if you are providing payment services (e-money/payment processing) under the Law governing the Payment System (2021); otherwise labour-law compliance via MIFOTRA | C31: BNR under the payment/banking frameworks and microfinance/credit laws for lending activities

Sheet Rates
A1: General | B1: Amount/Threshold | C1: Description
A2: Personal_Relief | B2: 0 | C2: RW₣ / month
A3: Insurance_Relief | B3: 0 | C3: RW₣ / month
A4: Business_Travel_Allowance_Deductible_Cap | B4: 0 | C4: No Monthly Cap
A5: Medical_Allowance_Deductible_Cap | B5: 0 | C5: No Monthly Cap
A6: RSSB_Medical_Insurance_Employee | B6: 0.075 | C6: Employee 7.5%
A7: RSSB_Medical_Insurance_Employer | B7: 0.075 | C7: Employer 7.5%
A8: RSSB_Medical_Maternity_Employee | B8: 0.003 | C8: Employee 0.3%
A9: RSSB_Medical_Maternity_Employer | B9: 0.003 | C9: Employer 0.3%
A10: RSSB_Medical_Pension_Employee | B10: 0.06 | C10: Employee 6%
A11: RSSB_Medical_Pension_Employer | B11: 0.06 | C11: Employer 6%
A12: Earned_Wage_Days | B12: =Inputs!B7 -> 30 | C12: Earned Wage Days
A13: Days in Month | B13: 30 | C13: Number of Days in Month
A14: Earned_Wage_Cap | B14: 0.45 | C14: Monthly cap on net pay
A16: PAYE_Tax_Bands
A17: Lower | B17: Upper | C17: Rate | D17: Tax
A18: 0 | B18: 60000 | C18: 0 | D18: =B18*C18 -> 0
A19: 60001 | B19: 100000 | C19: 0.1 | D19: =(B19-B18)*C19 -> 4000
A20: 100001 | B20: 200000 | C20: 0.2 | D20: =(B20-B19)*C20 -> 20000
A21: 200001 | C21: 0.3

Sheet Inputs
A1: Inputs
A2: Employee | B2: Sample Employee | C2: <-Input
A3: Gross_Pay_Employer | B3: 80000 | C3: <-Input
A4: Other_Remuneration_Employer [Incl. Bonuses, Travel, Cellphone, Housing Allowance, Car Allowance] | C4: <-Input
A5: Business_Travel_Allowance_Employer | C5: <-Input
A6: Medical_Cover_Employer | C6: <-Input
A7: Days_Worked | B7: 30 | C7: <-Input
A8: Mortgage_Interest_Contribution_Employee | C8: <-Input Not Required [Mabye Consider for More Advanced Modelling]
A9: Post-retirement_Medical Fund_Contribution_Employee | C9: <-Input Not Required [Mabye Consider for More Advanced Modelling]
A10: Provident_Fund_Contribution_Employee | C10: <-Input Not Required [Mabye Consider for More Advanced Modelling]
A11: Life_And_Health_Insurance_Contribution_Employee | C11: <-Input Not Required [Mabye Consider for More Advanced Modelling]

Sheet Workings
A1: Workings
A2: Employee | B2: =Inputs!B2 -> Sample Employee
A3: Gross_Pay_Employer | B3: =Inputs!B3 -> 80000
A4: Other_Remuneration_Employer [Incl. Bonuses, Travel, Cellphone, Housing Allowance, Car Allowance, Housing Allownace] | B4: =Inputs!B4 -> 0
A5: Business_Travel_Allowance_Employer | B5: =Inputs!B5 -> 0
A6: Medical_Cover_Employer | B6: =Inputs!B6 -> 0
A7: Mortgage_Interest_Contribution_Employee | B7: =Inputs!B8 -> 0
A8: Post-retirement_Medical Fund_Contribution_Employee | B8: =Inputs!B9 -> 0
A9: Provident_Fund_Contribution_Employee | B9: =Inputs!B10 -> 0
A10: Life_And_Health_Insurance_Contribution_Employee | B10: =Inputs!B11 -> 0
A11: Total_Income | B11: =SUM(B3:B10) -> 80000
A12: Business_Travel_Allowance_Deductible | B12: =-MAX(B5,Rates!B4) -> 0
A13: Medical_Cover_Employer_Deductible | B13: =-MAX(Rates!B5,Workings!B6) -> 0
A14: Taxable_Income | B14: =B11+SUM(B12:B13) -> 80000
A15: RSSB_Medical_Insurance_Employee | B15: =B11*Rates!B6 -> 6000
A16: RSSB_Medical_Maternity_Employee | B16: =B11*Rates!B8 -> 240
A17: RSSB_Medical_Pension_Employee | B17: =B11*Rates!B10 -> 4800
A18: RSSB_Medical_Insurance_Employer | B18: =Rates!B7*B11 -> 6000
A19: RSSB_Medical_Maternity_Employer | B19: =B11*Rates!B9 -> 240
A20: RSSB_Medical_Pension_Employer | B20: =B11*Rates!B11 -> 4800
A21: PAYE_Before_Relief | B21: =IF(B14>=Rates!A21,Rates!C21*(B14-Rates!A21)+Rates!D20+Rates!D19,0)+IF(AND(B14>=Rates!A20,B14<=Rates!B20),Rates!C20*(B14-Rates!A20)+Rates!D19)+IF(AND(B14>=Rates!A19,B14<=Rates!B19),Rates!C19*(B14-Rates!A19)+Rates!D18)+IF(B14<=Rates!B18,0,0) -> 1999.9
A22: Personal_Relief | B22: =Rates!B2 -> 0
A23: Insurance_Relief | B23: =Rates!B3 -> 0
A24: PAYE_After_Relief | B24: =MAX(B21-B22-B23,0) -> 1999.9
A25: Net_Pay | B25: =ROUND(B11+SUM(B12:B17)-B24,0) -> 169040
A26: Earned_Wage | B26: =B25*Inputs!B7/Rates!B13 -> 169040 | C26: <-Earned Wage
A27: Earned_Wage_Max_Cap | B27: =ROUND(IFERROR(B25*Rates!B14,0),0) -> 76068 | C27: <-Available Earned Wage Max
A28: Earned_Wage_Available | B28: =IFERROR(MIN(B26:B27),0) -> 76068 | C28: <-Available Earned Wage

Sheet Output
A1: Output
A2: Earned_Wage | B2: =Workings!B26 -> 169040
A3: Earned_Wage_Max_Cap | B3: =Workings!B27 -> 76068
A4: Earned_Wage_Available | B4: =Workings!B28 -> 76068
A5: Remittances
A6: RSSB_Medical_Insurance | B6: =Workings!B15+Workings!B18 -> 12000
A7: RSSB_Medical_Maternity | B7: =Workings!B16+Workings!B19 -> 480
A8: RSSB_Medical_Pension | B8: =Workings!B17+Workings!B20 -> 9600
A9: PAYE | B9: =Workings!B21 -> 1999.9
