Workbook

Sheet Notes
A1: Comprehensive Statutroy Acts & Legal Frameworks Matrix (Tanzania)
A2: This matrix outlines the key Statutory Acts & Legal References for statutory PAYE tax limits, rates, levies and reliefts.
A4: Income Tax Act (Cap 332, Laws of Tanzania)
A5: Description | B5: Reference | C5: Limit
A6: Personal relief | B6: N/A | C6: None. PAYE applies via resident bands (top rate 30%) and a flat 15% on employment income of non-residents (final tax).
A7: Medical reimbursements / employer medical insurance | B7: ITA (general employment-income rules) | C7: Typically excluded if it’s an actual reimbursement or employer policy paid for work purposes; otherwise taxable. (No statutory shilling cap stated in the Act; apply general benefit rules.)
A8: Business travel & accommodation (in course of duty) | B8: TRA – PAYE guidance | C8: Excluded where incurred/likely to be incurred in performing duties (documented).
A9: Housing benefit | B9: TRA – PAYE | C9: Taxable benefit = lower of (i) market rent or (ii) employer’s cost; less any employee contribution.
A10: Company car benefit | B10: ITA schedules / TRA | C10: Taxable annual value by engine size & age (e.g., ≤1000cc: TZS 250k if <5 yrs / 125k if >5 yrs; >3000cc: 1.5m / 750k).
A11: Subsidised/low-interest loan | B11: ITA | C11: Taxable benefit = difference between statutory/market rate and actual rate; include in PAYE base. (No fixed TZS cap; apply ITA method.)
A12: Employer pays employee’s tax | B12: ITA s.27(d) | C12: The “tax benefit” is grossed-up at 330% of tax paid on behalf of the employee (special quantification rule).
A13: The National Security Fund Act, 1997and National Social Security Fund (Amendment) Act, 2018 (NSSF NO. 50 of 2018)
A14: Description | B14: Reference | C14: Limit
A15: NSSF contributions | B15: NSSF Cap 50 | C15: Total 20% of employee’s gross salary (private sector). Employer may: 10% + 10%, or 15% employer + 5% employee, or remit full 20%. Employee share must not exceed 10%.
A16: National Health Insurance Fund (NHIF) Act of Tanzania (NHIF Act No. 8 of 1999) and Universal Health Coverage (UHC) Bill in 2022
A17: Description | B17: Reference | C17: Limit
A18: NHIF | B18: NHIF Cap 8 | C18: Common payroll configuration: 3% employer + 3% employee of monthly salary (legacy NHIF for PUBLIC sector employees).
A19: Universal Health Insurance Act, 2023 | B19: UHI Bill 2022 | C19: Mandates health insurance and obligates formal-sector employers to contribute; implementation details and exact payroll mechanics are being operationalised. Universal Health Coverage (UHC) Bill in 2022
A20: Finance Act, 2025
A21: Description | B21: Reference | C21: Limit
A22: Skills Development Levy (SDL) | B22: Finance Act, 2025 | C22: Mainland: 3.5% of monthly gross emoluments (employers with ≥10 employees). Zanzibar: 4%. Employer-paid.
A23: Workers’ Compensation Fund (WCF) | B23: Finance Act, 2025 | C23: Typical employer rate around 0.6% of cash wages.
A24: None
A25: Description | B25: Reference | C25: Limit
A26: Housing levy | B26: N/A | C26: Not applicable in Tanzania (Kenya-specific.)
A27: Public Service Superannuation Scheme Act, 2012
A28: Description | B28: Reference | C28: Limit
A29: Public-sector fund | B29: PSSSF Act 2012 | C29: Public employees contribute under PSSSF; rates and rules differ from NSSF (outside private-sector scope here). The Public Service Social Security Fund (PSSSF) in Tanzania has a total contribution rate of 20% of the employee's monthly basic salary. This total is split between the employer and the employee as follows: Employer Contribution: 15% of the employee's monthly salary Employee Contribution: 5% of the employee's monthly salary, which is deducted from their pay These rates are based on the employee's basic salary, excluding bonuses, overtime pay, or allowances. The employer is responsible for remitting the total 20% contribution to the PSSSF by the last day of the following month.
A30: Employment & Labour Relations Act (ELRA), 2004
A31: Description | B31: Reference | C31: Limit
A32: Permitted deductions (taxes, NSSF, agreed items, court orders, etc.) | B32: Employment & Labour Relations Act (ELRA), 2004 | C32: Deductions must be permitted by law/contract/consent; unlawful deductions are prohibited.
A33: Recovery of wage advances | B33: Employment (Protection of Wages) Regs., 1957 | C33: If recovering an advance, each instalment must not exceed one-third of the employee’s wage for the pay period.
A34: Earned Wage Access (EWA) / salary advances | B34: Employment & Labour Relations Act (ELRA), 2004 | C34: Treat as advance on wages already earned/due with written employee consent and payslip disclosure (not a loan). Ensure compliance with the 1/3 per-instalment cap when recovering advances.
A35: Feature | B35: Earned Wage Access (EWA) | C35: Traditional Loan
A36: Source of funds | B36: Employee’s already earned salary (portion of wages due) | C36: Third-party credit not yet earned
A37: Legal classification | B37: Advance on wages under the ELRA Act | C37: Credit facility under the Bank of Tanzania Act, the Microfinance Act, 2018, or other banking laws.
A38: Interest or finance charge | B38: Typically a small facilitation or service fee (not interest) | C38: Interest-bearing under the Microfinance Act, 2018 or Banking and Financial Institutions Act, 2006.
A39: Repayment source | B39: Automatically deducted from future salary payment | C39: Paid over time from future income according to agreed loan repayment terms.
A40: Regulatory body | B40: Bank of Tanzania (BoT) — under the National Payment Systems Act, 2015 for fintechs that process wage disbursements or payments. Ministry of Labour, Youth, Employment and Persons with Disability — under the Employment and Labour Relations Act, 2004 for compliance with wage deduction and advance rules (particularly the 1/3 recovery cap per pay period). | C40: Bank of Tanzania (BoT) — under the Banking and Financial Institutions Act, 2006 and the Microfinance Act, 2018 for loan, credit, or microfinance activities.

Sheet Rates
A1: General | B1: Amount/Threshold | C1: Description
A2: Personal_Relief | B2: 0 | C2: TZS / month
A3: Insurance_Relief | B3: 0 | C3: TZS / month
A4: Pension_Deductible_Cap | B4: 0 | C4: Monthly cap on deductible
A5: Housing_Deductible_Cap | B5: 0 | C5: Lower of (i) market rent or (ii) employer’s cost; less any employee contribution.
A6: Business Travel_Deductible_Cap | B6: 0 | C6: No Monthly cap on deductible
A7: Night-Out_Deductible_Cap | B7: 0 | C7: Daily cap on deductible
A8: Medical_Cover_Deductible_Cap | B8: 0 | C8: No Monthly cap on deductible
A9: Life_And_Health_Insurance_Deductible_Limit | B9: 0 | C9: Monthly cap on deductible
A10: NSSF_Employer_Rate | B10: 0.1 | C10: Employer 10%
A11: NSSF_Employee_Rate | B11: 0.1 | C11: Employee 10%
A12: SDL_Employer_Rate | B12: 0.035 | C12: Employer 3.5%
A13: SDL_Employee_Rate | B13: 0 | C13: Employee 0%
... A17: UHI_NHIF_Employee_Rate | B17: 0.03 | C17: Employee 3%
A18: Earned_Wage_Days | B18: =Inputs!B11 -> 30 | C18: Earned Wage Days
A19: Days in Month | B19: =_xlfn.DAYS(EOMONTH(TODAY(),0),(EOMONTH(TODAY(), - 1) + 0)) -> 30 | C19: Number of Days in Month
A20: Earned_Wage_Cap | B20: 0.3 | C20: Monthly cap on net pay
A22: PAYE_Tax_Bands
A23: Lower | B23: Upper | C23: Rate | D23: Tax
A24: 0 | B24: 270000 | C24: 0 | D24: =B24*C24 -> 0
A25: 270001 | B25: 520000 | C25: 0.08 | D25: =(B25-B24)*C25 -> 20000
A26: 520001 | B26: 760000 | C26: 0.2 | D26: =(B26-B25)*C26 -> 48000
A27: 760001 | B27: 1000000 | C27: 0.25 | D27: =(B27-B26)*C27 -> 60000
A28: 1000001 | C28: 0.3
A30: LST_Bands
A31: Lower | B31: Upper | C31: Tax
A32: 0 | B32: 100000 | C32: 0
A33: 100001 | B33: 200000 | C33: 5000
A34: 200001 | B34: 300000 | C34: 10000
A35: 300001 | B35: 400000 | C35: 20000
A36: 400001 | B36: 500000 | C36: 30000
A37: 500001 | B37: 600000 | C37: 40000
A38: 600001 | B38: 700000 | C38: 60000
A39: 700001 | B39: 800000 | C39: 70000
A40: 800001 | B40: 900000 | C40: 80000
A41: 900001 | B41: 1000000 | C41: 90000
A42: 10000000 | C42: 100000

Sheet Inputs
A1: Inputs
A2: Employee | B2: Sample Employee | C2: <-Input
A3: Gross_Pay_Employer | B3: 2000000 | C3: <-Input
A4: Other_Remuneration_Employer [Incl. Bonuses, Travel, Cellphone, Car Allowance] | C4: <-Input
A5: Business_Travel_&_Accommodation_Allowance_Employer | C5: <-Input
A6: Housing_Allowance_Employer | C6: <-Input
A7: NightOut_Allowance_Employer | C7: <-Input
A8: Pension_Cover_Employer | C8: <-Input
A9: Medical_Cover_Employer | C9: <-Input
A10: Life_Insurance_Cover_Employer | C10: <-Input
A11: Days_Worked | B11: 30 | C11: <-Input
A12: Mortgage_Interest_Contribution_Employee | C12: <-Input Not Required [Mabye Consider for More Advanced Modelling]
A13: Post-retirement_Medical Fund_Contribution_Employee | C13: <-Input Not Required [Mabye Consider for More Advanced Modelling]
A14: Provident_Fund_Contribution_Employee | C14: <-Input Not Required [Mabye Consider for More Advanced Modelling]
A15: Life_And_Health_Insurance_Contribution_Employee | C15: <-Input Not Required [Mabye Consider for More Advanced Modelling]

Sheet Workings
A1: Outputs
A2: Employee | B2: =Inputs!B2 -> Sample Employee
A3: Gross_Pay_Employer | B3: =Inputs!B3 -> 2000000
A4: Other_Remuneration_Employer [Incl. Bonuses, Travel, Cellphone, Housing Allowance, Car Allowance, Housing Allownace] | B4: =Inputs!B4 -> 0
A5: Business_Travel_Allowance_Employer | B5: =Inputs!B5 -> 0
A6: Housing_Allowance_Employer | B6: =Inputs!B6 -> 0
A7: NightOut_Allowance_Employer | B7: =Inputs!B7 -> 0
A8: Pension_Cover_Employer | B8: =Inputs!B8 -> 0
A9: Medical_Cover_Employer | B9: =Inputs!B9 -> 0
A10: Life_Insurance_Cover_Employer | B10: =Inputs!B10 -> 0
A11: Total_Income | B11: =SUM(B3:B10) -> 2000000
A12: Business_Travel_&_Accomodation_Allowance_Deductible | B12: =-MAX(B5,Rates!B6) -> 0
A13: Housing_Allowance_Deductible | B13: =-MAX(B6,Rates!B5) -> 0
A14: NightOut_Allowance_Deductible | B14: =-MIN(B7,Rates!$B$7) -> 0
A15: Pension_Cover_Deductible | B15: =-MIN(B8,Rates!$B$4) -> 0
A16: Medical_Cover_Employer_Deductible | B16: =-B9 -> 0
A17: Life_Insurance_Cover_Employer_Deductible | B17: =-MIN(B10,Rates!B9) -> 0
A18: NSSF_Employee | B18: =-Rates!B11*B11 -> -200000
A19: Total_Taxable_Income | B19: =SUM(B11:B18) -> 1800000
A20: NSSF_Employer | B20: =-Rates!B10*B11 -> -200000
A21: SDL_Employer | B21: =-Rates!B12*B11 -> -70000
A22: Workers_Compensation_Fund_Tariff_Employer | B22: =-Rates!B14*B11 -> -12000
A23: UHI_NHIF_Employer | B23: =-B11*Rates!B16 -> -60000
A24: UHI_NHIF_Employee | B24: =-B11*Rates!B17 -> -60000
A25: PAYE_Before_Relief | B25: =IF(B19>Rates!B24,Rates!D24,0)+IF(B19>Rates!B25,Rates!D25,0)+IF(B19>Rates!B26,Rates!D26,0)+IF(B19>Rates!B27,Rates!D27,0)+IF(B19>Rates!B27,(B19-Rates!B27)*Rates!C28,0)+IF(B19<Rates!B24,B19*Rates!C24)+IF(AND(B19>=Rates!A25,B19<Rates!B25),(B19-Rates!A25)*Rates!C25,0)+IF(AND(B19>=Rates!A26,B19<Rates!B26),(B19-Rates!A26)*Rates!C26,0)+IF(AND(B19>=Rates!A27,B19<Rates!B27),(B19-Rates!A27)*Rates!C27,0) -> 368000
A26: Personal_Relief | B26: =Rates!B2 -> 0
A27: Insurance_Relief | B27: =Rates!B3 -> 0
A28: PAYE_After_Relief | B28: =MAX(B25-B26-B27,0) -> 368000
A29: Net_Pay | B29: =B19-B28 -> 1432000
A30: Earned_Wage | B30: =ROUND(B29*Inputs!B11/Rates!B19,0) -> 1432000 | C30: <-Earned Wage
A31: Earned_Wage_Max_Cap | B31: =ROUND(IFERROR(B29*Rates!B20,0),0) -> 429600 | C31: <-Available Earned Wage Max
A32: Earned_Wage_Available | B32: =IFERROR(MIN(B30:B31),0) -> 429600 | C32: <-Available Earned Wage

Sheet Output
A1: Output
A2: Earned_Wage | B2: =Workings!B30 -> 1432000
A3: Earned_Wage_Max_Cap | B3: =Workings!B31 -> 429600
A4: Earned_Wage_Available | B4: =Workings!B32 -> 429600
A5: Remittances
A6: NSSF_Employee | B6: =-Workings!B18 -> 200000
A7: NSSF_Employer | B7: =-Workings!B20 -> 200000
A8: SDL_Employer | B8: =-Workings!B21 -> 70000
A9: Workers_Compensation_Fund_Tariff_Employer | B9: =-Workings!B22 -> 12000
A10: UHI_NHIF_Employer | B10: =-Workings!B23 -> 60000
A11: UHI_NHIF_Employee | B11: =-Workings!B24 -> 60000
A12: PAYE | B12: =Workings!B25 -> 368000
