Workbook

Sheet Notes
A1: Comprehensive Statutroy Acts & Legal Frameworks Matrix (Kenya)
A2: This matrix outlines the key Statutory Acts & Legal References for statutory PAYE tax limits, rates, levies and reliefts.
A4: Income Tax Act (Cap 470, Laws of Kenya)
A5: Description | B5: Reference | C5: Limit
A6: Personal Relief | B6: Section 30 and Third Schedule | C6: Ksh 2,400/month
A7: Insurance Relief | B7: Section 31 | C7: allows up to 15% of premiums paid for life, education, or health policies (subject to limit).
A8: Mortgage Interest Deduction | B8: Section 15(3)(b) | C8: up to KSh 300,000 per year (≈ KSh 25,000/month)
A9: Post-Retirement Medical Fund Deductions | B9: Section 22B | C9: Ksh 5,000/month
A10: Provident & Pension Fund Deductions | B10: Section 22A | C10: KSh 30,000/month
A11: Meal, Night-out, and Other Allowances | B11: Taxable per Section 5(2)(a); deductibility guided by allowable expense limits in Schedule 3. | C11: KSh 5,000 cap (Night-Out) / KSh 2,000 daily (Meal)
A12: Life and Health Insurance Relief | B12: Section 31 | C12: Capped at 15% of annual premium, limited to KSh 5,000/month
A13: National Social Security Fund Act, 2013 (NSSF Act No. 45 of 2013)
A14: Description | B14: Reference | C14: Limit
A15: NSSF Employee Contribution (Tier I & II) | B15: Section 18(1). NSSFI Tier II updated through Legal Notice No. 17 of 2024). Employer matches employee contribution 1:1. The contributions are deductible under Section 22 of the Income Tax Act. | C15: Tier I: 6% of pensionable earnings up to KSh 7,000. Tier II: 6% on next band up to KSh 72,000
A16: National Health Insurance Fund Act, 1998 (Amended 2021) / Social Health Insurance Act, 2023
A17: Description | B17: Reference | C17: Limit
A18: SHIF / NHIF Contributions | B18: Section 26: Employer and employee rates based on income bands. Contributions are deductible under Section 15(3) of the Income Tax Act. | C18: 2.75% of gross pay contribution rate
A19: Affordable Housing Levy (AHL) – Finance Act, 2023
A20: Description | B20: Reference | C20: Limit
A21: AHL | B21: Collected by employers under the Income Tax (Affordable Housing Levy) Regulations, 2023. Filed monthly via PAYE returns under the Income Tax Act (Cap 470). Effective from July 2023 (replacing the earlier Housing Fund contributions). | C21: 1.5% of gross monthly pay (employee) + 1.5% (employer match).
A22: Retirement Benefits Act, 1997
A23: Description | B23: Reference | C23: Limit
A24: Pension and provident fund contributions and benefit deductions | B24: Supports limits aligned to Section 22A of the Income Tax Act | C24: KSh 20,000 or 30% of salary per month, whichever lower
A25: Employment Act, 2007
A26: Description | B26: Reference | C26: Limit
A27: Earned wage access (EWA) or advance payments | B27: Section 19(1)(e) authorizes statutory deductions from wages. Since EWA represents earned income, not credit, it: Is not subject to the Banking Act or CBK lending regulations. However, if the provider adds interest or structured credit terms, the service risks reclassification as a credit product, subject to the Microfinance Act (2006) or CBK (Digital Credit Providers) Regulations, 2022. However, Section 19(3) of the Act sets an important restriction: "The total amount of all deductions from wages in any one wage period shall not exceed two-thirds of such wages.” | C27: Earned Wage Access (EWA) is not a loan under Kenyan law if: 1) The amount represents wages already earned; 2) The employee consents to the advance; and 3) The deduction is made under Section 19(1)(e) of the Employment Act, 2007 and the deduction on payday must appear on the payslip as “salary advance” or “earned wage access”. Deductions must not exceed ⅔ (67%) of wages in a pay period.
A28: Feature | B28: Earned Wage Access (EWA) | C28: Traditional Loan
A29: Source of funds | B29: Employee’s already earned salary (portion of wages due) | C29: Third-party credit not yet earned
A30: Legal classification | B30: Advance on wages under the Employment Act | C30: Credit facility under the Banking/Finance Acts
A31: Interest or finance charge | B31: Typically a small facilitation or service fee (not interest) | C31: Interest-bearing under the Credit or Microfinance Acts
A32: Repayment source | B32: Automatically deducted from future salary payment | C32: Paid over time from future income
A33: Regulatory body | B33: Ministry of Labour (Employment Act) | C33: Central Bank of Kenya (CBK Act, Banking Act, Microfinance Act)

Sheet Rates
A1: General | B1: Amount/Threshold | C1: Description
A2: Personal_Relief | B2: 2400 | C2: KES / month
A3: Insurance_Relief | B3: 0 | C3: KES / month (edit if applicable)
A4: Housing_Levy_Rate | B4: 0.015 | C4: AHL as fraction of Gross (default 1.5%)
A5: SHIF_Flat_Rate | B5: 0.0275 | C5: If Use_SHIF_Table=FALSE, SHIF = Gross*rate
A6: Pension_Deductible_Cap | B6: 30000 | C6: Monthly cap on deductible
A7: Meals_Deductible_Cap | B7: 5000 | C7: Monthly cap on deductible
A8: Night-Out_Deductible_Cap | B8: 2000 | C8: Daily cap on deductible
A9: Post-Retirement_Medical_Fund_Deductible_Cap | B9: 5000 | C9: Monthly cap on deductible
A10: Mortgage_Interest_Deductible_Cap | B10: 25000 | C10: Monthly cap on deductible
A11: Provident_Fund_Deductible_Cap | B11: 30000 | C11: Monthly cap on deductible
A12: Life_And_Health_Insurance_Deductible_Limit | B12: =60000/12 -> 5000 | C12: Monthly cap on deductible
A13: NSSF_Tier1_Ceiling | B13: 7000 | C13: Tier I ceiling
A14: NSSF_Tier2_Ceiling | B14: 72000 | C14: Tier II ceiling
A15: NSSF_Employee_Rate | B15: 0.06 | C15: Employee 6%
A16: AHL_Employee_Rate | B16: 0.015 | C16: Employee 1.5%
A17: AHL_Employee_Rate | B17: 0.015 | C17: Employer 1.5%
A18: Life_And_Health_Insurance_Rate | B18: 0.15 | C18: Life and Health Insurance 15%
A19: Provident_Fund_Deductible_Rate | B19: 0.3 | C19: Upto 30%
A20: Earned_Wage_Days | B20: =Inputs!B9 -> 30 | C20: Earned Wage Days
A21: Days in Month | B21: 30 | C21: Number of Days in Month
A22: Earned_Wage_Cap | B22: 0.6 | C22: Monthly cap on net pay
A24: PAYE_Tax_Bands
A25: Lower | B25: Upper | C25: Rate | D25: Tax
A26: 0 | B26: 24000 | C26: 0.1 | D26: =B26*C26 -> 2400
A27: 24000 | B27: 32333 | C27: 0.25 | D27: =(B27-B26)*C27 -> 2083.25
A28: 32333 | B28: 500000 | C28: 0.3 | D28: =(B28-B27)*C28 -> 140300.1
A29: 500000 | B29: 800000 | C29: 0.325 | D29: =(B29-B28)*C29 -> 97500
A30: 800000 | C30: 0.35

Sheet Inputs
A1: Inputs
A2: Employee | B2: Sample Employee | C2: <-Input
A3: Gross_Pay_Employer | B3: 35000 | C3: <-Input
A4: Other_Remuneration_Employer [Incl. Bonuses, Travel, Cellphone, Housing Allowance, Car Allowance] | C4: <-Input
A5: Meal_Allowance_Employer | C5: <-Input
A6: NightOut_Allowance_Employer | C6: <-Input
A7: Pension_Cover_Employer | C7: <-Input
A8: Medical_Cover_Employer | C8: <-Input
A9: Days_Worked | B9: 30 | C9: <-Input
A10: Mortgage_Interest_Contribution_Employee | C10: <-Input Not Required [Mabye Consider for More Advanced Modelling]
A11: Post-retirement_Medical Fund_Contribution_Employee | C11: <-Input Not Required [Mabye Consider for More Advanced Modelling]
A12: Provident_Fund_Contribution_Employee | C12: <-Input Not Required [Mabye Consider for More Advanced Modelling]
A13: Life_And_Health_Insurance_Contribution_Employee | C13: <-Input Not Required [Mabye Consider for More Advanced Modelling]

Sheet Workings
A1: Workings
A2: Employee | B2: =Inputs!B2 -> Sample Employee
A3: Gross_Pay_Employer | B3: =Inputs!B3 -> 35000
A4: Other_Remuneration_Employer [Incl. Bonuses, Travel, Cellphone, Housing Allowance, Car Allowance, Housing Allownace] | B4: =Inputs!B4 -> 0
A5: Meal_Allowance_Employer | B5: =Inputs!B5 -> 0
A6: NightOut_Allowance_Employer | B6: =Inputs!B6 -> 0
A7: Pension_Cover_Employer | B7: =Inputs!B7 -> 0
A8: Medical_Cover_Employer | B8: =Inputs!B8 -> 0
A9: Mortgage_Interest_Contribution_Employee | B9: =Inputs!B10 -> 0
A10: Post-retirement_Medical Fund_Contribution_Employee | B10: =Inputs!B11 -> 0
A11: Provident_Fund_Contribution_Employee | B11: =Inputs!B12 -> 0
A12: Life_And_Health_Insurance_Contribution_Employee | B12: =Inputs!B13 -> 0
A13: Total_Income | B13: =SUM(B3:B12) -> 35000
A14: Meal_Allowance_Deductible | B14: =-MIN(B5,Rates!B7) -> 0
A15: NightOut_Allowance_Deductible | B15: =-MIN(B6,Rates!$B$8*Rates!B21) -> 0
A16: Pension_Cover_Deductible | B16: =-MIN(B7,Rates!$B$6) -> 0
A17: Medical_Cover_Employer_Deductible | B17: =-B8 -> 0
A18: Post-retirement_Medical Fund_Cover_Deductible | B18: =MIN(B9,Rates!B9) -> 0
A19: Mortgage_Interest_Deductible | B19: =MIN(B10,Rates!$B$10) -> 0
A20: Provident_Fund_Deductible | B20: =MIN(B11,Rates!B11,B3*Rates!B19) -> 0
A21: Life_And_Health_Insurance_Contribution_Cover | B21: =MIN(Rates!$B$18*Workings!B12,Rates!B12) -> 0
A22: NSSF_1_Employee | B22: =-Rates!B15*MIN(Workings!B13,Rates!B13) -> -420
A23: NSSF_2_Employee | B23: =-Rates!B15*MAX(MIN(B13, Rates!B14)-Rates!B13, 0) -> -1680
A24: SHIF_Employee | B24: =-IF(B13=0,0,IF(B13*Rates!$B$5<300,300,B13*Rates!$B$5)) -> -962.5
A25: Housing Levy_Employee | B25: =-B13*Rates!B16 -> -525
A26: Taxable_Income | B26: =B13+SUM(B14:B25) -> 31412.5
A27: PAYE_Before_Relief | B27: =IF(B26>Rates!B26,Rates!D26,0)+IF(B26>Rates!B27,Rates!D27,0)+IF(B26>Rates!B28,Rates!D28,0)+IF(B26>Rates!B29,Rates!D29,0)+IF(B26>Rates!B29,(B26-Rates!B29)*Rates!C30,0)+IF(B26<Rates!B26,B26*Rates!C26)+IF(AND(Workings!B26>=Rates!A27,Workings!B26<Rates!B27),(Workings!B26-Rates!A27)*Rates!C27,0)+IF(AND(Workings!B26>=Rates!A28,Workings!B26<Rates!B28),(Workings!B26-Rates!A28)*Rates!C28,0)+IF(AND(Workings!B26>=Rates!A29,Workings!B26<Rates!B29),(Workings!B26-Rates!A29)*Rates!C29,0) -> 4253.125
A28: Personal_Relief | B28: =Rates!B2 -> 2400
A29: Insurance_Relief | B29: =MIN(B21*Rates!B18,Rates!B12) -> 0
A30: PAYE_After_Relief | B30: =MAX(B27-B28-B29,0) -> 1853.125
A31: Net_Pay | B31: =ROUND(B13+SUM(B14:B25)-B30,0) -> 29559
A32: Earned_Wage | B32: =B31*Inputs!B9/Rates!B21 -> 29559 | C32: <-Earned Wage
A33: Earned_Wage_Max_Cap | B33: =ROUND(IFERROR(B31*Rates!B22,0),0) -> 17735 | C33: <-Available Earned Wage Max
A34: Earned_Wage_Available | B34: =IFERROR(MIN(B32:B33),0) -> 17735 | C34: <-Available Earned Wage

Sheet Output
A1: Output
A2: Earned_Wage | B2: =Workings!B32 -> 29559
A3: Earned_Wage_Max_Cap | B3: =Workings!B33 -> 17735
A4: Earned_Wage_Available | B4: =Workings!B34 -> 17735
A5: Remittances
A6: NSSF_1 | B6: =-Workings!B22 -> 420
A7: NSSF_2 | B7: =-Workings!B23 -> 1680
A8: SHIF | B8: =-Workings!B24 -> 962.5
A9: Housing Levy | B9: =-Workings!B25 -> 525
A10: PAYE | B10: =Workings!B30 -> 1853.125
