Workbook

Sheet Notes
A1: Comprehensive Statutroy Acts & Legal Frameworks Matrix (Uganda)
A2: This matrix outlines the key Statutory Acts & Legal References for statutory PAYE tax limits, rates, levies and reliefts.
A4: Income Tax Act (Cap 340, Laws of Uganda)
A5: Description | B5: Reference | C5: Limit
A6: Personal Relief | B6: N/A | C6: None. Uganda does not grant a universal personal relief/credit. PAYE is computed using bands with a tax-free monthly threshold of UGX 235,000 (UGX 2,820,000 p.a.)
A7: Insurance Relief | B7: N/A | C7: None. Uganda does not grant a universal personal relief/credit.
A8: Medical reimbursements (including employer-paid medical insurance) | B8: ITA s.19(2)(b); definition of “medical expenses” in s.19 | C8: Excluded from employment income when the employer reimburses/pays medical expenses. “Medical expenses” includes medical insurance premiums. No statutory shilling cap stated.
A9: Business travel & accommodation reimbursement/allowance (in course of duty) | B9: ITA s.19(2)(b) | C9: Excluded from employment income if incurred or likely to be incurred in performing employment duties. No fixed per-diem cap in the Act.
A10: Employer contributions to a retirement fund (resident retirement fund) | B10: ITA s.19(2) (exempt items) | C10: Excluded from the employee’s employment income (i.e., not taxable to the employee).
A11: Small de-minimis benefits | B11: Practice notes / summaries | C11: A benefit provided to an employee not exceeding UGX 10,000 in a month is treated as non-taxable (exclusion).
A12: Meals/refreshments provided on equal terms to all staff, on employer premises | B12: ITA s.19(2); also deductibility note | C12: Excluded from employment income for the employee; employer’s deduction allowed where the value is included in employment income or provided on equal terms to all workers.
A13: Housing / company car / low-interest loans (valuation rules) | B13: Schedules & guidance under ITA s.19 | C13: Taxable benefits with specific valuation rules (e.g., housing “lower of market rent less employee contribution or 15% of emoluments”; car benefit formula (20% × A × B/C) – D; loan benefit = (statutory – actual rate) × principal/12).
A14: National Social Security Fund (Amendment) Act, 2021 (NSSF NO. 222 of Act 2021) and National Social Security Fund (Amendment) Act, 1985 (NSSF NO. 230 of 1985)
A15: Description | B15: Reference | C15: Limit
A16: NSSF contributions (Employer + Employee) | B16: NSSF Act (Cap 230) | C16: Employee: 5% of gross monthly wage; Employer: 10% of gross monthly wage → Total 15%. Practically interpreted as cash pay (salary/wages and cash allowances). Non-cash benefits are not explicitly included or excluded in statute wording; treat reimbursements/benefits-in-kind with care and document your position.
A17: None
A18: Description | B18: Reference | C18: Limit
A19: National Health Insurance levy | B19: N/A | C19: No national SHI/NHIF payroll levy in force as of FY 2024/25–2025/26. Parliament passed an NHIS Bill in 2021, but Presidential assent has not occurred and the scheme remains stalled / being re-tabled; thus no statutory deductions yet.
A20: None
A21: Description | B21: Reference | C21: Limit
A22: Housing levy | B22: N/A | C22: Not applicable in Uganda. (Kenya-specific.)
A23: Uganda Retirement Benefits Regulatory Authority (URBRA) Act, 2011
A24: Description | B24: Reference | C24: Limit
A25: Employer contributions to resident retirement fund for employee | B25: ITA s.19(2) | C25: Excluded from employee’s employment income. Generally exempt from income tax (unlike gratuity/terminal benefits, which are taxable as employment income).
A26: Employment Act, 2006
A27: Description | B27: Reference | C27: Limit
A28: Permitted deductions (taxes, NSSF, agreed items, court orders, etc.) | B28: Employment Act s.46 | C28: Deductions must be authorised by law/contract/employee consent; certain deductions prohibited.
A29: Attachment/overall cap | B29: Employment Act s.46(3) | C29: Any attachment of wages (by operation of law) shall not exceed two-thirds (⅔) of remuneration due for the pay period. (Useful ceiling when you design any payroll deductions, including salary advances/EWA).
A30: Earned Wage Access (EWA) / salary advances | B30: Employment Act framework on deductions & advances | C30: Treated as advance of wages already earned / due, not a loan, where the employee consents and payroll reflects the deduction; ensure total deductions respect the ⅔ cap and other permitted-deduction rules. (No central-bank licensing applies if it remains a wages advance, not credit.)
A31: Feature | B31: Earned Wage Access (EWA) | C31: Traditional Loan
A32: Source of funds | B32: Employee’s already earned salary (portion of wages due) | C32: Third-party credit not yet earned
A33: Legal classification | B33: Advance on wages under the Employment Act | C33: Credit facility under the Uganda Microfinance Regulatory Authority (UMRA)
A34: Interest or finance charge | B34: Typically a small facilitation or service fee (not interest) | C34: Interest-bearing under the Uganda Microfinance Regulatory Authority (UMRA)
A35: Repayment source | B35: Automatically deducted from future salary payment | C35: Paid over time from future income
A36: Regulatory body | B36: Central Bank of Uganda (National Payment Systems Act, 2020 (NPSA) and the National Payment Systems Regulations, 2021) | C36: Uganda Microfinance Regulatory Authority (UMRA)

Sheet Rates
A1: General | B1: Amount/Threshold | C1: Description
A2: Personal_Relief | B2: 0 | C2: UGX / month
A3: Insurance_Relief | B3: 0 | C3: UGX / month
A4: Pension_Deductible_Cap | B4: 0 | C4: No Monthly cap on deductible
A5: Meals_Deductible_Cap | B5: 0 | C5: Monthly cap on deductible
A6: Business Travel_Deductible_Cap | B6: 0 | C6: No Monthly cap on deductible
A7: Night-Out_Deductible_Cap | B7: 0 | C7: Daily cap on deductible
A8: Medical_Cover_Deductible_Cap | B8: 0 | C8: No Monthly cap on deductible
A9: Life_And_Health_Insurance_Deductible_Limit | B9: 0 | C9: No Monthly cap on deductible
A10: NSSF_Employer_Rate | B10: 0.1 | C10: Employer 10%
A11: NSSF_Employee_Rate | B11: 0.05 | C11: Employee 6%
A12: Earned_Wage_Days | B12: =Inputs!B11 -> 30 | C12: Earned Wage Days
A13: Days in Month | B13: =_xlfn.DAYS(EOMONTH(TODAY(),0),(EOMONTH(TODAY(), - 1) + 0)) -> 30 | C13: Number of Days in Month
A14: Earned_Wage_Cap | B14: 0.6 | C14: Monthly cap on net pay
A16: PAYE_Tax_Bands
A17: Lower | B17: Upper | C17: Rate | D17: Tax
A18: 0 | B18: 235000 | C18: 0 | D18: =B18*C18 -> 0
A19: 235001 | B19: 335000 | C19: 0.1 | D19: =(B19-B18)*C19 -> 10000
A20: 335001 | B20: 410000 | C20: 0.2 | D20: =(B20-B19)*C20 -> 15000
A21: 410001 | B21: 10000000 | C21: 0.3 | D21: =(B21-B20)*C21 -> 2877000
A22: 1000000 | C22: 0.4
A24: LST_Bands
A25: Lower | B25: Upper | C25: Tax
A26: 0 | B26: 100000 | C26: 0
A27: 100001 | B27: 200000 | C27: 5000
A28: 200001 | B28: 300000 | C28: 10000
A29: 300001 | B29: 400000 | C29: 20000
A30: 400001 | B30: 500000 | C30: 30000
A31: 500001 | B31: 600000 | C31: 40000
A32: 600001 | B32: 700000 | C32: 60000
A33: 700001 | B33: 800000 | C33: 70000
A34: 800001 | B34: 900000 | C34: 80000
A35: 900001 | B35: 1000000 | C35: 90000
A36: 10000000 | C36: 100000

Sheet Inputs
A1: Inputs
A2: Employee | B2: Sample Employee | C2: <-Input
A3: Gross_Pay_Employer | B3: 10000000 | C3: <-Input
A4: Other_Remuneration_Employer [Incl. Bonuses, Travel, Cellphone, Housing Allowance, Car Allowance] | C4: <-Input
A5: Business_Travel_Allowance_Employer | C5: <-Input
A6: Meal_Allowance_Employer | C6: <-Input
A7: NightOut_Allowance_Employer | C7: <-Input
A8: Pension_Cover_Employer | C8: <-Input
A9: Medical_Cover_Employer | C9: <-Input
A10: Life_Insurance_Cover_Employer | C10: <-Input
A11: Days_Worked | B11: 30 | C11: <-Input
A12: Mortgage_Interest_Contribution_Employee | C12: <-Input Not Required [Mabye Consider for More Advanced Modelling]
A13: Post-retirement_Medical Fund_Contribution_Employee | C13: <-Input Not Required [Mabye Consider for More Advanced Modelling]
A14: Provident_Fund_Contribution_Employee | C14: <-Input Not Required [Mabye Consider for More Advanced Modelling]
A15: Life_And_Health_Insurance_Contribution_Employee | C15: <-Input Not Required [Mabye Consider for More Advanced Modelling]

Sheet Workings
A1: Outputs
A2: Employee | B2: =Inputs!B2 -> Sample Employee
A3: Gross_Pay_Employer | B3: =Inputs!B3 -> 10000000
A4: Other_Remuneration_Employer [Incl. Bonuses, Travel, Cellphone, Housing Allowance, Car Allowance, Housing Allownace] | B4: =Inputs!B4 -> 0
A5: Business_Travel_Allowance_Employer | B5: =Inputs!B5 -> 0
A6: Meal_Allowance_Employer | B6: =Inputs!B6 -> 0
A7: NightOut_Allowance_Employer | B7: =Inputs!B7 -> 0
A8: Pension_Cover_Employer | B8: =Inputs!B8 -> 0
A9: Medical_Cover_Employer | B9: =Inputs!B9 -> 0
A10: Life_Insurance_Cover_Employer | B10: =Inputs!B10 -> 0
A11: Total_Income | B11: =SUM(B3:B10) -> 10000000
A12: Business_Travel_Allowance_Deductible | B12: =-MAX(B5,Rates!B5) -> 0
A13: Meal_Allowance_Deductible | B13: =-MIN(B6,Rates!B5) -> 0
A14: NightOut_Allowance_Deductible | B14: =-MIN(B7,Rates!$B$7) -> 0
A15: Pension_Cover_Deductible | B15: =-MAX(B8,Rates!$B$4) -> 0
A16: Medical_Cover_Employer_Deductible | B16: =-B9 -> 0
A17: Life_Insurance_Cover_Employer_Deductible | B17: =-MAX(B10,Rates!B9) -> 0
A18: LST_Deductible | B18: =-(IF(AND(B11>=Rates!A26,B11<=Rates!B26),Rates!C26,0)+IF(AND(B11>=Rates!A27,B11<=Rates!B27),Rates!C27,0)+IF(AND(B11>=Rates!A28,B11<=Rates!B28),Rates!C28,0)++IF(AND(B11>=Rates!A29,B11<=Rates!B29),Rates!C29,0)+IF(AND(B11>=Rates!A30,B11<=Rates!B30),Rates!C31,0)+IF(AND(B11>=Rates!A32,B11<=Rates!B32),Rates!C32,0)+IF(AND(B11>=Rates!A33,B11<=Rates!B33),Rates!C33,0)+IF(AND(B11>=Rates!A34,B11<=Rates!B34),Rates!C34,0)+IF(AND(B11>=Rates!A35,B11<=Rates!B35),Rates!C35,0)+IF(B11>=Rates!B36,Rates!C36,0)) -> -100000
A19: Total_Income | B19: =SUM(B11:B18) -> 9900000
A20: NSSF_Employee | B20: =-Rates!B11*B11 -> -500000
A21: NSSF_Employer | B21: =-Rates!B10*B11 -> -1000000
A22: PAYE_Before_Relief | B22: =IF(B19>Rates!B18,Rates!D18,0)+IF(B19>Rates!B19,Rates!D19,0)+IF(B19>Rates!B20,Rates!D20,0)+IF(B19>Rates!B21,Rates!D21,0)+IF(B19>Rates!B21,(B19-Rates!B21)*Rates!C22,0)+IF(B19<Rates!B18,B19*Rates!C18)+IF(AND(B19>=Rates!A19,B19<Rates!B19),(B19-Rates!A19)*Rates!C19,0)+IF(AND(B19>=Rates!A20,B19<Rates!B20),(B19-Rates!A20)*Rates!C20,0)+IF(AND(B19>=Rates!A21,B19<Rates!B21),(B19-Rates!A21)*Rates!C21,0) -> 2871999.7
A23: Personal_Relief | B23: =Rates!B2 -> 0
A24: Insurance_Relief | B24: =Rates!B3 -> 0
A25: PAYE_After_Relief | B25: =MAX(B22-B23-B24,0) -> 2871999.7
A26: Net_Pay | B26: =B19+B20-B25 -> 6528000.3
A27: Earned_Wage | B27: =ROUND(B26*Inputs!B11/Rates!B13,0) -> 6528000 | C27: <-Earned Wage
A28: Earned_Wage_Max_Cap | B28: =ROUND(IFERROR(B26*Rates!B14,0),0) -> 3916800 | C28: <-Available Earned Wage Max
A29: Earned_Wage_Available | B29: =IFERROR(MIN(B27:B28),0) -> 3916800 | C29: <-Available Earned Wage

Sheet Output
A1: Output
A2: Earned_Wage | B2: =Workings!B27 -> 6528000
A3: Earned_Wage_Max_Cap | B3: =Workings!B28 -> 3916800
A4: Earned_Wage_Available | B4: =Workings!B29 -> 3916800
A5: Remittances
A6: LST | B6: =-Workings!B18 -> 100000
A7: NSSF_Employee | B7: =-Workings!B20 -> 500000
A8: NSSF_Employer | B8: =-Workings!B21 -> 1000000
A9: PAYE | B9: =Workings!B25 -> 2871999.7
